ketool/__init__.py
ketool/__version__.py
ketool/date.py
ketool-0.0.3.dist-info/LICENSE
ketool-0.0.3.dist-info/METADATA
ketool-0.0.3.dist-info/WHEEL
ketool-0.0.3.dist-info/top_level.txt
ketool-0.0.3.dist-info/RECORD
