Metadata-Version: 2.1
Name: ketool
Version: 0.0.3
Summary: A set of tools that make coding more simpler for python.
Home-page: https://github.com/liukecode/ketool.git
Author: Liuke
Author-email: UNKNOWN
License: UNKNOWN
Keywords: python,KeTool
Platform: all
Classifier: Programming Language :: Python :: 3
Classifier: License :: OSI Approved :: MIT License
Classifier: Operating System :: OS Independent
Requires-Python: >=3
